contextflow/__init__.py
contextflow/backends.py
contextflow/context.py
contextflow/memory.py
contextflow/test.ipynb
contextflow/utils.py
contextflow-1.10.0.dist-info/METADATA
contextflow-1.10.0.dist-info/WHEEL
contextflow-1.10.0.dist-info/RECORD
