Metadata-Version: 2.4
Name: contextflow
Version: 1.10.0
Summary: Large Language Models Tools
Project-URL: Homepage, https://github.com/Equiron-AI/contextflow
Project-URL: Repository, https://github.com/Equiron-AI/contextflow
Project-URL: Issues, https://github.com/Equiron-AI/contextflow/issues
Author-email: Vladimir Petrukhin <man4j@ya.ru>
License: MIT
Classifier: Development Status :: 4 - Beta
Classifier: Operating System :: OS Independent
Classifier: Programming Language :: Python :: 3
Requires-Python: >=3.10
Requires-Dist: jinja2
Requires-Dist: pytz
Requires-Dist: sseclient-py
Requires-Dist: transformers
